lektor_deploy_ipfs.py
lektor_deploy_ipfs-1.0.0.dist-info/METADATA
lektor_deploy_ipfs-1.0.0.dist-info/WHEEL
lektor_deploy_ipfs-1.0.0.dist-info/entry_points.txt
lektor_deploy_ipfs-1.0.0.dist-info/top_level.txt
lektor_deploy_ipfs-1.0.0.dist-info/RECORD
