Metadata-Version: 2.1
Name: lektor-deploy-ipfs
Version: 1.0.0
Summary: Deploy your static Lektor website to IPFS!
Author-email: Erin Yuki Schlarb <erin-dev@ninetailed.ninja>
License: LGPLv3
Keywords: Lektor plugin
Classifier: Environment :: Plugins
Classifier: Environment :: Web Environment
Classifier: Framework :: Lektor
Classifier: Environment :: Plugins
Classifier: Intended Audience :: Developers
Classifier: License :: OSI Approved :: GNU Lesser General Public License v3 or later (LGPLv3+)
Requires-Python: >=3.8
Requires-Dist: dns-lexicon
Requires-Dist: httpx
Requires-Dist: ipfshttpclient
